dmsdownloader/__init__.py
dmsdownloader/attributes.py
dmsdownloader/color_format.py
dmsdownloader/custom_logger.py
dmsdownloader/main.py
dmsdownloader-1.0.1.dist-info/METADATA
dmsdownloader-1.0.1.dist-info/WHEEL
dmsdownloader-1.0.1.dist-info/top_level.txt
dmsdownloader-1.0.1.dist-info/RECORD
