Metadata-Version: 2.1
Name: dmsdownloader
Version: 1.0.1
Summary: Download and Upload Files to DMS
Author: MTLM
Keywords: python,dms,downloader
Classifier: Development Status :: 1 - Planning
Classifier: Intended Audience :: Developers
Classifier: Programming Language :: Python :: 3
Classifier: Operating System :: Unix
Classifier: Operating System :: MacOS :: MacOS X
Requires-Dist: tqdm >=4.66.1
Requires-Dist: requests >=2.31.0
